odoo/addons/hr_timesheet_editable_top/README.rst
odoo/addons/hr_timesheet_editable_top/__init__.py
odoo/addons/hr_timesheet_editable_top/__manifest__.py
odoo/addons/hr_timesheet_editable_top/i18n/hr_timesheet_editable_top.pot
odoo/addons/hr_timesheet_editable_top/i18n/it.po
odoo/addons/hr_timesheet_editable_top/readme/CONTRIBUTORS.md
odoo/addons/hr_timesheet_editable_top/readme/DESCRIPTION.md
odoo/addons/hr_timesheet_editable_top/static/description/icon.png
odoo/addons/hr_timesheet_editable_top/static/description/index.html
odoo/addons/hr_timesheet_editable_top/views/hr_analytic_timesheet.xml
odoo_addon_hr_timesheet_editable_top-18.0.1.0.0.1.dist-info/METADATA
odoo_addon_hr_timesheet_editable_top-18.0.1.0.0.1.dist-info/WHEEL
odoo_addon_hr_timesheet_editable_top-18.0.1.0.0.1.dist-info/top_level.txt
odoo_addon_hr_timesheet_editable_top-18.0.1.0.0.1.dist-info/RECORD
